pytest_webtest_extras/__init__.py
pytest_webtest_extras/extras.py
pytest_webtest_extras/plugin.py
pytest_webtest_extras/utils.py
pytest_webtest_extras/resources/error.png
pytest_webtest_extras/resources/style.css
pytest_webtest_extras-1.3.1.dist-info/entry_points.txt
pytest_webtest_extras-1.3.1.dist-info/WHEEL
pytest_webtest_extras-1.3.1.dist-info/METADATA
pytest_webtest_extras-1.3.1.dist-info/RECORD
