Metadata-Version: 2.3
Name: pytest-webtest-extras
Version: 1.3.1
Summary: Pytest plugin to enhance pytest-html and allure reports of webtest projects by adding screenshots, comments and webpage sources.
Keywords: pytest,selenium,playwright,webtest,webtesting
Author-email: Harmin Parra Rueda <harmin.rueda@gmail.com>
Requires-Python: >=3.9
Classifier: Framework :: Pytest
Classifier: License :: OSI Approved :: MIT License
Classifier: Topic :: Software Development :: Quality Assurance
Classifier: Topic :: Software Development :: Testing
Requires-Dist: pytest >= 7.0.0
Requires-Dist: pytest-html >= 4.0.0
Requires-Dist: pyyaml >= 6.0.2
